{
  "requestId": "",
  "code": "0000",
  "msg": "Success",
  "recordsTotal": 10000,
  "data": [
    {
      "dramaId": 39040,
      "dramaType": "TV",
      "title": "红尘依莎",
      "score": "8.0",
      "seasonNo": 0,
      "coverUrl": "http://img.juquanquanapp.com/img/img/20220224/o_ef4eea006b494a03beac88e9029e216c.jpg",
      "cover3Url": null,
      "vipFlag": false,
      "alias": "红尘依莎",
      "year": "2013",
      "producerRegion": "泰国",
      "plotType": "爱情,剧情",
      "actor": null,
      "subTitle": "月亮姐年代剧",
      "coverUrlInfo": null,
      "cover3UrlInfo": null,
      "episodeInfo": "连载中,不定期更新"
    },
    {
      "dramaId": 39036,
      "dramaType": "TV",
      "title": "青年维兰德第二季",
      "score": "7.8",
      "seasonNo": 2,
      "coverUrl": "http://img.juquanquanapp.com/img/img/20220223/o_6388d433032644d1b5be3430c2a80ea1.jpg",
      "cover3Url": null,
      "vipFlag": false,
      "alias": "青年维兰德 第二季",
      "year": "2022",
      "producerRegion": "美国",
      "plotType": "剧情,悬疑,惊悚,犯罪",
      "actor": null,
      "subTitle": "青年警探",
      "coverUrlInfo": null,
      "cover3UrlInfo": null,
      "episodeInfo": "未开播"
    },
    {
      "dramaId": 39032,
      "dramaType": "TV",
      "title": "终局",
      "score": "0.0",
      "seasonNo": 0,
      "coverUrl": "http://img.juquanquanapp.com/img/img/20220224/o_43efe799cb004123a2c840427a467a51.jpg",
      "cover3Url": null,
      "vipFlag": false,
      "alias": "终局",
      "year": "2022",
      "producerRegion": "美国",
      "plotType": "剧情,犯罪",
      "actor": null,
      "subTitle": "双女主犯罪剧",
      "coverUrlInfo": null,
      "cover3UrlInfo": null,
      "episodeInfo": "每周一更新"
    },
    {
      "dramaId": 39031,
      "dramaType": "TV",
      "title": "疫厢情缘第二季",
      "score": "0.0",
      "seasonNo": 2,
      "coverUrl": "http://img.juquanquanapp.com/img/img/20220219/o_291254d4a076446cb3cc5ca0bcf9efd4.jpg",
      "cover3Url": null,
      "vipFlag": false,
      "alias": "疫厢情缘 第二季",
      "year": "2022",
      "producerRegion": "其他",
      "plotType": "剧情,同性",
      "actor": null,
      "subTitle": "疫情下的爱情故事",
      "coverUrlInfo": null,
      "cover3UrlInfo": null,
      "episodeInfo": "连载中,不定期更新"
    },
    {
      "dramaId": 39030,
      "dramaType": "TV",
      "title": "Calming Signal_汪喵汪喵",
      "score": "7.0",
      "seasonNo": 0,
      "coverUrl": "http://img.juquanquanapp.com/img/img/20220221/o_75e25d195e4741fca4effd976f2b153f.jpg",
      "cover3Url": null,
      "vipFlag": false,
      "alias": "Calming Signal_汪喵汪喵",
      "year": "2022",
      "producerRegion": "韩国",
      "plotType": "喜剧,爱情",
      "actor": null,
      "subTitle": "猫系男×狗系女",
      "coverUrlInfo": null,
      "cover3UrlInfo": null,
      "episodeInfo": "每周六更新"
    },
    {
      "dramaId": 39029,
      "dramaType": "TV",
      "title": "Oh! Boarding House",
      "score": "0.0",
      "seasonNo": 0,
      "coverUrl": "http://img.juquanquanapp.com/img/img/20220221/o_d8f7c85431d04b00a29a7f155fb04fdd.jpg",
      "cover3Url": null,
      "vipFlag": false,
      "alias": "Oh! Boarding House",
      "year": "2022",
      "producerRegion": "韩国",
      "plotType": "爱情,同性",
      "actor": null,
      "subTitle": "房东×奇怪租客",
      "coverUrlInfo": null,
      "cover3UrlInfo": null,
      "episodeInfo": "每周二更新"
    },
    {
      "dramaId": 39016,
      "dramaType": "TV",
      "title": "饼干老师星星糖",
      "score": "7.6",
      "seasonNo": 0,
      "coverUrl": "http://img.juquanquanapp.com/img/img/20220221/o_e655c7912793448385cdc0b5d59db334.jpg",
      "cover3Url": null,
      "vipFlag": false,
      "alias": "饼干老师星星糖",
      "year": "2006",
      "producerRegion": "韩国",
      "plotType": "爱情",
      "actor": null,
      "subTitle": "孔孝真孔刘师生恋",
      "coverUrlInfo": null,
      "cover3UrlInfo": null,
      "episodeInfo": "已完结"
    },
    {
      "dramaId": 39012,
      "dramaType": "TV",
      "title": "liar",
      "score": "6.3",
      "seasonNo": 0,
      "coverUrl": "http://img.juquanquanapp.com/img/img/20220216/o_6f3c650b46234d22a504653cbcbdd885.jpg",
      "cover3Url": null,
      "vipFlag": false,
      "alias": "liar",
      "year": "2022",
      "producerRegion": "日本",
      "plotType": "爱情",
      "actor": null,
      "subTitle": "谎言与欲望",
      "coverUrlInfo": null,
      "cover3UrlInfo": null,
      "episodeInfo": "连载中,不定期更新"
    },
    {
      "dramaId": 39003,
      "dramaType": "TV",
      "title": "大叔在为我的恋情应援（脑内）",
      "score": "6.5",
      "seasonNo": 0,
      "coverUrl": "http://img.juquanquanapp.com/img/img/20220216/o_61fc391f91bd4055a2b6a9e55cb861a1.jpg",
      "cover3Url": null,
      "vipFlag": false,
      "alias": "大叔在为我的恋情应援（脑内）",
      "year": "2022",
      "producerRegion": "日本",
      "plotType": "喜剧,爱情",
      "actor": null,
      "subTitle": "大叔的打call",
      "coverUrlInfo": null,
      "cover3UrlInfo": null,
      "episodeInfo": "连载中,不定期更新"
    },
    {
      "dramaId": 39002,
      "dramaType": "VARIETY",
      "title": "黄阿丽：风流女子",
      "score": "8.3",
      "seasonNo": 0,
      "coverUrl": "http://img.juquanquanapp.com/img/img/20220216/o_4c2058eba8474ced8f70812e8779a683.jpg",
      "cover3Url": null,
      "vipFlag": false,
      "alias": "黄阿丽：风流女子",
      "year": "2022",
      "producerRegion": "美国",
      "plotType": "脱口秀",
      "actor": null,
      "subTitle": "风流亚裔",
      "coverUrlInfo": null,
      "cover3UrlInfo": null,
      "episodeInfo": "已完结"
    },
    {
      "dramaId": 39001,
      "dramaType": "TV",
      "title": "邪神的天秤 警视厅公安分析班",
      "score": "7.5",
      "seasonNo": 0,
      "coverUrl": "http://img.juquanquanapp.com/img/img/20220215/o_3089869c920045c2890f2ea0e99b773a.jpg",
      "cover3Url": null,
      "vipFlag": false,
      "alias": "邪神的天秤 警视厅公安分析班",
      "year": "2022",
      "producerRegion": "日本",
      "plotType": "悬疑,犯罪",
      "actor": null,
      "subTitle": "模仿神话犯罪",
      "coverUrlInfo": null,
      "cover3UrlInfo": null,
      "episodeInfo": "连载中,不定期更新"
    },
    {
      "dramaId": 39000,
      "dramaType": "MOVIE",
      "title": "巨型漏洞",
      "score": "6.4",
      "seasonNo": 1,
      "coverUrl": "http://img.juquanquanapp.com/img/img/20220215/o_804fe27218184eed9788cbae09d6bc6f.jpg",
      "cover3Url": null,
      "vipFlag": false,
      "alias": "巨型漏洞",
      "year": "2022",
      "producerRegion": "法国",
      "plotType": "喜剧,科幻",
      "actor": null,
      "subTitle": "乌龙智慧管家",
      "coverUrlInfo": null,
      "cover3UrlInfo": null,
      "episodeInfo": ""
    },
    {
      "dramaId": 38999,
      "dramaType": "MOVIE",
      "title": "回心转意",
      "score": "6.6",
      "seasonNo": 1,
      "coverUrl": "http://img.juquanquanapp.com/img/img/20220215/o_237f89404d0240b0b436f009151df68c.jpg",
      "cover3Url": null,
      "vipFlag": false,
      "alias": "回心转意",
      "year": "2022",
      "producerRegion": "美国",
      "plotType": "喜剧,爱情",
      "actor": null,
      "subTitle": "失恋的陌生男女",
      "coverUrlInfo": null,
      "cover3UrlInfo": null,
      "episodeInfo": ""
    },
    {
      "dramaId": 38998,
      "dramaType": "MOVIE",
      "title": "战场上的布谷鸟",
      "score": "8.5",
      "seasonNo": 1,
      "coverUrl": "http://img.juquanquanapp.com/img/img/20220217/o_682e8b74710040ed860a046027f4e02b.jpg",
      "cover3Url": null,
      "vipFlag": false,
      "alias": "战场上的布谷鸟",
      "year": "2002",
      "producerRegion": "其他",
      "plotType": "剧情,喜剧,战争",
      "actor": null,
      "subTitle": "爱战胜了死亡",
      "coverUrlInfo": null,
      "cover3UrlInfo": null,
      "episodeInfo": ""
    },
    {
      "dramaId": 38997,
      "dramaType": "TV",
      "title": "噬谎者-鞍马兰子篇",
      "score": "6.8",
      "seasonNo": 0,
      "coverUrl": "http://img.juquanquanapp.com/img/img/20220214/o_a660c25b05934bc48d5016eadccd8024.jpg",
      "cover3Url": null,
      "vipFlag": false,
      "alias": "噬谎者-鞍马兰子篇",
      "year": "2022",
      "producerRegion": "日本",
      "plotType": "剧情",
      "actor": null,
      "subTitle": "赌徒的契约游戏",
      "coverUrlInfo": null,
      "cover3UrlInfo": null,
      "episodeInfo": "连载中,不定期更新"
    },
    {
      "dramaId": 38996,
      "dramaType": "MOVIE",
      "title": "好运山姆",
      "score": "7.1",
      "seasonNo": 1,
      "coverUrl": "http://img.juquanquanapp.com/img/img/20220211/o_05f6cce31bdd40919f64e62dc43fd9f8.jpg",
      "cover3Url": null,
      "vipFlag": false,
      "alias": "好运山姆",
      "year": "2016",
      "producerRegion": "法国",
      "plotType": "动作,冒险",
      "actor": null,
      "subTitle": "为了阿尔及利亚",
      "coverUrlInfo": null,
      "cover3UrlInfo": null,
      "episodeInfo": ""
    },
    {
      "dramaId": 38995,
      "dramaType": "VARIETY",
      "title": "欢天喜地七仙男",
      "score": "9.2",
      "seasonNo": 0,
      "coverUrl": "http://img.juquanquanapp.com/img/img/20220211/o_7e0ace55afd84306b8efa5deca2b31ec.jpg",
      "cover3Url": null,
      "vipFlag": false,
      "alias": "欢天喜地七仙男",
      "year": "2008",
      "producerRegion": "日本",
      "plotType": "喜剧",
      "actor": null,
      "subTitle": "爆笑日式谈话节目",
      "coverUrlInfo": null,
      "cover3UrlInfo": null,
      "episodeInfo": "连载中,不定期更新"
    },
    {
      "dramaId": 38994,
      "dramaType": "MOVIE",
      "title": "向着巅峰",
      "score": "7.3",
      "seasonNo": 1,
      "coverUrl": "http://img.juquanquanapp.com/img/img/20220211/o_3bc1e91fd96748a2a36b5b79e2cacddc.jpg",
      "cover3Url": null,
      "vipFlag": false,
      "alias": "向着巅峰",
      "year": "2017",
      "producerRegion": "法国",
      "plotType": "动作",
      "actor": null,
      "subTitle": "极限登峰",
      "coverUrlInfo": null,
      "cover3UrlInfo": null,
      "episodeInfo": ""
    },
    {
      "dramaId": 38992,
      "dramaType": "DOCUMENTARY",
      "title": "亚洲艺文眼",
      "score": "8.6",
      "seasonNo": 0,
      "coverUrl": "http://img.juquanquanapp.com/img/img/20220211/o_deee86e2117d4c59adfdace5461c94fa.jpg",
      "cover3Url": null,
      "vipFlag": false,
      "alias": "亚洲艺文眼",
      "year": "2022",
      "producerRegion": "德国",
      "plotType": "冒险,传记",
      "actor": null,
      "subTitle": "艺术爱好者导览",
      "coverUrlInfo": null,
      "cover3UrlInfo": null,
      "episodeInfo": "连载中,不定期更新"
    },
    {
      "dramaId": 38991,
      "dramaType": "COMIC",
      "title": "幻灭第四季",
      "score": "9.2",
      "seasonNo": 4,
      "coverUrl": "http://img.juquanquanapp.com/img/img/20220211/o_3f1a2b847a2645ddb99f429330a7eba0.jpg",
      "cover3Url": null,
      "vipFlag": false,
      "alias": "幻灭 第四季",
      "year": "2022",
      "producerRegion": "美国",
      "plotType": "喜剧,动作,冒险,奇幻,动画",
      "actor": null,
      "subTitle": "崩坏梦王国",
      "coverUrlInfo": null,
      "cover3UrlInfo": null,
      "episodeInfo": "未开播"
    },
    {
      "dramaId": 38988,
      "dramaType": "VARIETY",
      "title": "爱情盲选：日本篇",
      "score": "7.9",
      "seasonNo": 0,
      "coverUrl": "http://img.juquanquanapp.com/img/img/20220209/o_33e13de80538418ca26c7a1ee276b996.jpg",
      "cover3Url": null,
      "vipFlag": false,
      "alias": "爱情盲选：日本篇",
      "year": "2022",
      "producerRegion": "日本",
      "plotType": "真人秀,爱情",
      "actor": null,
      "subTitle": "蒙眼选对象？",
      "coverUrlInfo": null,
      "cover3UrlInfo": null,
      "episodeInfo": "连载中,不定期更新"
    }
  ]
}